[{"challenge_id": 30054567, "username": "thkang91", "registration_date": "2016-06-17", "submission_date": "2016-06-20"}, {"challenge_id": 30054567, "username": "genycopedison", "registration_date": "2016-06-17", "submission_date": ""}, {"challenge_id": 30054567, "username": "dingjian", "registration_date": "2016-06-17", "submission_date": ""}, {"challenge_id": 30054567, "username": "xiufei", "registration_date": "2016-06-17", "submission_date": ""}, {"challenge_id": 30054567, "username": "ecavalier313", "registration_date": "2016-06-17", "submission_date": "2016-06-20"}, {"challenge_id": 30054567, "username": "gzhyh", "registration_date": "2016-06-17", "submission_date": ""}, {"challenge_id": 30054567, "username": "elwinwang1993", "registration_date": "2016-06-17", "submission_date": "2016-06-21"}, {"challenge_id": 30054567, "username": "panoptimum", "registration_date": "2016-06-17", "submission_date": ""}, {"challenge_id": 30054567, "username": "cam.ashwini", "registration_date": "2016-06-17", "submission_date": "2016-06-19"}, {"challenge_id": 30054567, "username": "gando19850304", "registration_date": "2016-06-17", "submission_date": ""}, {"challenge_id": 30054567, "username": "codingdrone", "registration_date": "2016-06-17", "submission_date": ""}, {"challenge_id": 30054567, "username": "gets0ul", "registration_date": "2016-06-17", "submission_date": ""}, {"challenge_id": 30054567, "username": "ondrejba", "registration_date": "2016-06-17", "submission_date": "2016-06-20"}, {"challenge_id": 30054567, "username": "blu3fox", "registration_date": "2016-06-17", "submission_date": ""}, {"challenge_id": 30054567, "username": "diogenesjcs", "registration_date": "2016-06-18", "submission_date": ""}, {"challenge_id": 30054567, "username": "rakeshk_87", "registration_date": "2016-06-18", "submission_date": ""}, {"challenge_id": 30054567, "username": "krisjen", "registration_date": "2016-06-18", "submission_date": ""}, {"challenge_id": 30054567, "username": "mtj111", "registration_date": "2016-06-18", "submission_date": ""}, {"challenge_id": 30054567, "username": "sunbinbrother", "registration_date": "2016-06-18", "submission_date": ""}, {"challenge_id": 30054567, "username": "xinscirpt", "registration_date": "2016-06-19", "submission_date": ""}, {"challenge_id": 30054567, "username": "cairi", "registration_date": "2016-06-19", "submission_date": ""}, {"challenge_id": 30054567, "username": "cinscript", "registration_date": "2016-06-19", "submission_date": "2016-06-19"}, {"challenge_id": 30054567, "username": "wcheung", "registration_date": "2016-06-20", "submission_date": ""}, {"challenge_id": 30054567, "username": "testxusanping", "registration_date": "2016-06-20", "submission_date": ""}, {"challenge_id": 30054567, "username": "danag", "registration_date": "2016-06-20", "submission_date": ""}]