[{"challenge_id": 30086999, "username": "siddu_91", "registration_date": "2019-03-27", "submission_date": ""}, {"challenge_id": 30086999, "username": "snakecode", "registration_date": "2019-03-27", "submission_date": ""}, {"challenge_id": 30086999, "username": "nupurp", "registration_date": "2019-03-27", "submission_date": ""}, {"challenge_id": 30086999, "username": "kalindikumari", "registration_date": "2019-03-27", "submission_date": ""}, {"challenge_id": 30086999, "username": "khanfaraz", "registration_date": "2019-03-26", "submission_date": "2019-03-27"}, {"challenge_id": 30086999, "username": "codejam", "registration_date": "2019-03-26", "submission_date": "2019-03-27"}, {"challenge_id": 30086999, "username": "bpalleri", "registration_date": "2019-03-26", "submission_date": "2019-03-28"}, {"challenge_id": 30086999, "username": "phead", "registration_date": "2019-03-26", "submission_date": ""}, {"challenge_id": 30086999, "username": "codingdrone", "registration_date": "2019-03-26", "submission_date": ""}, {"challenge_id": 30086999, "username": "krisjen", "registration_date": "2019-03-26", "submission_date": ""}, {"challenge_id": 30086999, "username": "soso0574", "registration_date": "2019-03-26", "submission_date": ""}, {"challenge_id": 30086999, "username": "kiranm0", "registration_date": "2019-03-26", "submission_date": "2019-03-27"}, {"challenge_id": 30086999, "username": "vanitaw", "registration_date": "2019-03-26", "submission_date": "2019-03-28"}, {"challenge_id": 30086999, "username": "lieutenantroger", "registration_date": "2019-03-26", "submission_date": "2019-03-28"}, {"challenge_id": 30086999, "username": "mayur.joshi", "registration_date": "2019-03-26", "submission_date": "2019-03-27"}, {"challenge_id": 30086999, "username": "drasticdpk", "registration_date": "2019-03-26", "submission_date": "2019-03-27"}, {"challenge_id": 30086999, "username": "picachui", "registration_date": "2019-03-26", "submission_date": "2019-03-27"}, {"challenge_id": 30086999, "username": "ku244426", "registration_date": "2019-03-26", "submission_date": ""}, {"challenge_id": 30086999, "username": "gando19850304", "registration_date": "2019-03-26", "submission_date": ""}, {"challenge_id": 30086999, "username": "tabjulaakhil", "registration_date": "2019-03-26", "submission_date": ""}, {"challenge_id": 30086999, "username": "integratiab", "registration_date": "2019-03-26", "submission_date": ""}, {"challenge_id": 30086999, "username": "applehit16", "registration_date": "2019-03-26", "submission_date": ""}, {"challenge_id": 30086999, "username": "rohitgupta_", "registration_date": "2019-03-26", "submission_date": ""}, {"challenge_id": 30086999, "username": "fhyrdz", "registration_date": "2019-03-26", "submission_date": ""}, {"challenge_id": 30086999, "username": "fauzanmaulidi", "registration_date": "2019-03-26", "submission_date": ""}, {"challenge_id": 30086999, "username": "vikasverma", "registration_date": "2019-03-26", "submission_date": "2019-03-28"}, {"challenge_id": 30086999, "username": "gauravseta", "registration_date": "2019-03-26", "submission_date": "2019-03-27"}, {"challenge_id": 30086999, "username": "trevor7", "registration_date": "2019-03-26", "submission_date": ""}, {"challenge_id": 30086999, "username": "prabhsimran", "registration_date": "2019-03-26", "submission_date": ""}, {"challenge_id": 30086999, "username": "bela123", "registration_date": "2019-03-26", "submission_date": ""}, {"challenge_id": 30086999, "username": "gurpreetchhabra", "registration_date": "2019-03-26", "submission_date": ""}, {"challenge_id": 30086999, "username": "jobee", "registration_date": "2019-03-26", "submission_date": ""}, {"challenge_id": 30086999, "username": "smaraki410", "registration_date": "2019-03-26", "submission_date": ""}, {"challenge_id": 30086999, "username": "satkan", "registration_date": "2019-03-26", "submission_date": "2019-03-27"}, {"challenge_id": 30086999, "username": "dagasahab2007", "registration_date": "2019-03-26", "submission_date": ""}, {"challenge_id": 30086999, "username": "julia_vladi", "registration_date": "2019-03-26", "submission_date": "2019-03-28"}, {"challenge_id": 30086999, "username": "jackgid16", "registration_date": "2019-03-26", "submission_date": "2019-03-27"}, {"challenge_id": 30086999, "username": "chaithanyapk", "registration_date": "2019-03-26", "submission_date": "2019-03-27"}, {"challenge_id": 30086999, "username": "phoenix1992", "registration_date": "2019-03-26", "submission_date": ""}, {"challenge_id": 30086999, "username": "tennkei", "registration_date": "2019-03-26", "submission_date": "2019-03-28"}, {"challenge_id": 30086999, "username": "nhlaksmaestro", "registration_date": "2019-03-26", "submission_date": ""}, {"challenge_id": 30086999, "username": "subhu", "registration_date": "2019-03-26", "submission_date": ""}, {"challenge_id": 30086999, "username": "iversonlv", "registration_date": "2019-03-26", "submission_date": ""}, {"challenge_id": 30086999, "username": "indhu_92", "registration_date": "2019-03-26", "submission_date": ""}, {"challenge_id": 30086999, "username": "rajakannu", "registration_date": "2019-03-26", "submission_date": ""}, {"challenge_id": 30086999, "username": "sraarum", "registration_date": "2019-03-26", "submission_date": ""}, {"challenge_id": 30086999, "username": "pirosl_tc", "registration_date": "2019-03-26", "submission_date": ""}, {"challenge_id": 30086999, "username": "jackychan", "registration_date": "2019-03-26", "submission_date": ""}, {"challenge_id": 30086999, "username": "muzehyun", "registration_date": "2019-03-27", "submission_date": "2019-03-29"}, {"challenge_id": 30086999, "username": "ibrahimhrp", "registration_date": "2019-03-27", "submission_date": "2019-03-27"}, {"challenge_id": 30086999, "username": "spatel6", "registration_date": "2019-03-27", "submission_date": ""}, {"challenge_id": 30086999, "username": "developer_pra", "registration_date": "2019-03-27", "submission_date": ""}, {"challenge_id": 30086999, "username": "linuxuser", "registration_date": "2019-03-27", "submission_date": ""}, {"challenge_id": 30086999, "username": "mirajkhan", "registration_date": "2019-03-27", "submission_date": ""}, {"challenge_id": 30086999, "username": "ooo-oly", "registration_date": "2019-03-27", "submission_date": ""}, {"challenge_id": 30086999, "username": "dhanvana", "registration_date": "2019-03-27", "submission_date": ""}]