[{"challenge_id": 30052340, "username": "pfilippi", "registration_date": "2015-12-03", "submission_date": ""}, {"challenge_id": 30052340, "username": "superastrom", "registration_date": "2015-12-03", "submission_date": ""}, {"challenge_id": 30052340, "username": "son4moon", "registration_date": "2015-12-03", "submission_date": ""}, {"challenge_id": 30052340, "username": "vimrc", "registration_date": "2015-12-03", "submission_date": ""}, {"challenge_id": 30052340, "username": "codingdrone", "registration_date": "2015-12-03", "submission_date": ""}, {"challenge_id": 30052340, "username": "sapila", "registration_date": "2015-12-03", "submission_date": ""}, {"challenge_id": 30052340, "username": "renqingwei123", "registration_date": "2015-12-04", "submission_date": ""}, {"challenge_id": 30052340, "username": "billthu", "registration_date": "2015-12-04", "submission_date": ""}, {"challenge_id": 30052340, "username": "chensiji1989", "registration_date": "2015-12-04", "submission_date": ""}, {"challenge_id": 30052340, "username": "testxusanping", "registration_date": "2015-12-04", "submission_date": ""}, {"challenge_id": 30052340, "username": "lanchongyizu", "registration_date": "2015-12-04", "submission_date": ""}, {"challenge_id": 30052340, "username": "alec-hewitt", "registration_date": "2015-12-04", "submission_date": "2015-12-08"}, {"challenge_id": 30052340, "username": "mulish", "registration_date": "2015-12-04", "submission_date": ""}, {"challenge_id": 30052340, "username": "peterbest", "registration_date": "2015-12-04", "submission_date": ""}, {"challenge_id": 30052340, "username": "besabestin", "registration_date": "2015-12-04", "submission_date": ""}, {"challenge_id": 30052340, "username": "blu3fox", "registration_date": "2015-12-04", "submission_date": ""}, {"challenge_id": 30052340, "username": "phead", "registration_date": "2015-12-04", "submission_date": ""}, {"challenge_id": 30052340, "username": "jaindsonvs", "registration_date": "2015-12-04", "submission_date": ""}, {"challenge_id": 30052340, "username": "eurafaels", "registration_date": "2015-12-04", "submission_date": ""}, {"challenge_id": 30052340, "username": "fireant", "registration_date": "2015-12-04", "submission_date": ""}, {"challenge_id": 30052340, "username": "sunbinbrother", "registration_date": "2015-12-05", "submission_date": ""}, {"challenge_id": 30052340, "username": "heslil", "registration_date": "2015-12-05", "submission_date": "2015-12-08"}, {"challenge_id": 30052340, "username": "ttayo", "registration_date": "2015-12-05", "submission_date": ""}, {"challenge_id": 30052340, "username": "mparlaktuna", "registration_date": "2015-12-05", "submission_date": ""}, {"challenge_id": 30052340, "username": "billsedison", "registration_date": "2015-12-05", "submission_date": "2015-12-08"}, {"challenge_id": 30052340, "username": "tuxing", "registration_date": "2015-12-05", "submission_date": ""}, {"challenge_id": 30052340, "username": "code_now", "registration_date": "2015-12-05", "submission_date": ""}, {"challenge_id": 30052340, "username": "killtur", "registration_date": "2015-12-06", "submission_date": ""}, {"challenge_id": 30052340, "username": "chenxiaotemp", "registration_date": "2015-12-06", "submission_date": ""}, {"challenge_id": 30052340, "username": "xiufei", "registration_date": "2015-12-06", "submission_date": ""}, {"challenge_id": 30052340, "username": "fish00", "registration_date": "2015-12-06", "submission_date": ""}, {"challenge_id": 30052340, "username": "wcheung", "registration_date": "2015-12-06", "submission_date": ""}, {"challenge_id": 30052340, "username": "dontsoft", "registration_date": "2015-12-06", "submission_date": ""}, {"challenge_id": 30052340, "username": "fip", "registration_date": "2015-12-07", "submission_date": ""}, {"challenge_id": 30052340, "username": "tongkunvwang", "registration_date": "2015-12-07", "submission_date": ""}, {"challenge_id": 30052340, "username": "basus", "registration_date": "2015-12-08", "submission_date": ""}, {"challenge_id": 30052340, "username": "naeem95m", "registration_date": "2015-12-08", "submission_date": ""}, {"challenge_id": 30052340, "username": "linuxgeek", "registration_date": "2015-12-08", "submission_date": ""}]