[{"challenge_id": 30048269, "username": "sah2ed", "registration_date": "2015-01-01", "submission_date": ""}, {"challenge_id": 30048269, "username": "mulish", "registration_date": "2015-01-01", "submission_date": ""}, {"challenge_id": 30048269, "username": "cursor", "registration_date": "2015-01-02", "submission_date": ""}, {"challenge_id": 30048269, "username": "sunbinbrother", "registration_date": "2015-01-03", "submission_date": ""}, {"challenge_id": 30048269, "username": "xin135", "registration_date": "2015-01-03", "submission_date": "2015-01-03"}]