[{"challenge_id": 30055290, "username": "eng01", "registration_date": "2016-09-23", "submission_date": "2016-10-14"}, {"challenge_id": 30055290, "username": "sutowo", "registration_date": "2016-09-23", "submission_date": ""}, {"challenge_id": 30055290, "username": "tumeo", "registration_date": "2016-09-23", "submission_date": ""}, {"challenge_id": 30055290, "username": "iz4fl4me", "registration_date": "2016-09-23", "submission_date": ""}, {"challenge_id": 30055290, "username": "loeduduts", "registration_date": "2016-09-23", "submission_date": "2016-10-03"}, {"challenge_id": 30055290, "username": "codingdrone", "registration_date": "2016-09-23", "submission_date": ""}, {"challenge_id": 30055290, "username": "sonal_jain", "registration_date": "2016-09-23", "submission_date": ""}, {"challenge_id": 30055290, "username": "teevics", "registration_date": "2016-09-23", "submission_date": "2016-09-27"}, {"challenge_id": 30055290, "username": "pun_aga", "registration_date": "2016-09-23", "submission_date": ""}, {"challenge_id": 30055290, "username": "tuan.ngv", "registration_date": "2016-09-23", "submission_date": ""}, {"challenge_id": 30055290, "username": "penpo", "registration_date": "2016-09-23", "submission_date": ""}, {"challenge_id": 30055290, "username": "budihartono", "registration_date": "2016-09-23", "submission_date": ""}, {"challenge_id": 30055290, "username": "sweta.singh", "registration_date": "2016-09-23", "submission_date": ""}, {"challenge_id": 30055290, "username": "fhipu", "registration_date": "2016-09-23", "submission_date": "2016-09-27"}, {"challenge_id": 30055290, "username": "gando19850304", "registration_date": "2016-09-23", "submission_date": ""}, {"challenge_id": 30055290, "username": "pandorabox", "registration_date": "2016-09-23", "submission_date": "2016-10-03"}, {"challenge_id": 30055290, "username": "abhinav27", "registration_date": "2016-09-24", "submission_date": ""}, {"challenge_id": 30055290, "username": "blu3fox", "registration_date": "2016-09-23", "submission_date": ""}, {"challenge_id": 30055290, "username": "krisjen", "registration_date": "2016-09-23", "submission_date": ""}, {"challenge_id": 30055290, "username": "restoe_boemi", "registration_date": "2016-09-24", "submission_date": "2016-10-03"}, {"challenge_id": 30055290, "username": "f0rc0d3r", "registration_date": "2016-09-24", "submission_date": "2016-09-27"}, {"challenge_id": 30055290, "username": "mfikrifadli", "registration_date": "2016-09-25", "submission_date": "2016-09-27"}, {"challenge_id": 30055290, "username": "hydrone", "registration_date": "2016-09-24", "submission_date": ""}, {"challenge_id": 30055290, "username": "preti67", "registration_date": "2016-09-24", "submission_date": ""}, {"challenge_id": 30055290, "username": "asyphx", "registration_date": "2016-09-25", "submission_date": "2016-09-27"}, {"challenge_id": 30055290, "username": "riopurba", "registration_date": "2016-09-25", "submission_date": "2016-10-03"}, {"challenge_id": 30055290, "username": "gusnendar", "registration_date": "2016-09-25", "submission_date": ""}, {"challenge_id": 30055290, "username": "qualitycore", "registration_date": "2016-09-26", "submission_date": "2016-09-27"}, {"challenge_id": 30055290, "username": "lunana", "registration_date": "2016-09-26", "submission_date": ""}, {"challenge_id": 30055290, "username": "cupuabis", "registration_date": "2016-09-26", "submission_date": ""}, {"challenge_id": 30055290, "username": "rainforest", "registration_date": "2016-09-26", "submission_date": ""}, {"challenge_id": 30055290, "username": "holmes_ia", "registration_date": "2016-09-26", "submission_date": ""}, {"challenge_id": 30055290, "username": "light_ray", "registration_date": "2016-09-26", "submission_date": ""}, {"challenge_id": 30055290, "username": "deviam", "registration_date": "2016-09-26", "submission_date": ""}, {"challenge_id": 30055290, "username": "poundinc_tc", "registration_date": "2016-09-26", "submission_date": ""}, {"challenge_id": 30055290, "username": "dawnb", "registration_date": "2016-09-27", "submission_date": "2016-10-03"}, {"challenge_id": 30055290, "username": "pinakimishra95", "registration_date": "2016-09-28", "submission_date": "2016-09-29"}]