[{"challenge_id": 30059954, "username": "nofear", "registration_date": "2017-10-20", "submission_date": "2017-10-23"}, {"challenge_id": 30059954, "username": "egislr", "registration_date": "2017-10-20", "submission_date": ""}, {"challenge_id": 30059954, "username": "grv.ashu", "registration_date": "2017-10-21", "submission_date": ""}, {"challenge_id": 30059954, "username": "dendyh7", "registration_date": "2017-10-20", "submission_date": "2017-10-23"}, {"challenge_id": 30059954, "username": "yoki", "registration_date": "2017-10-20", "submission_date": ""}, {"challenge_id": 30059954, "username": "spacemonkey125", "registration_date": "2017-10-20", "submission_date": "2017-10-23"}, {"challenge_id": 30059954, "username": "riopurba", "registration_date": "2017-10-20", "submission_date": "2017-10-23"}, {"challenge_id": 30059954, "username": "handiputra", "registration_date": "2017-10-20", "submission_date": "2017-10-23"}, {"challenge_id": 30059954, "username": "immakid", "registration_date": "2017-10-20", "submission_date": ""}, {"challenge_id": 30059954, "username": "jeniroxy", "registration_date": "2017-10-20", "submission_date": ""}, {"challenge_id": 30059954, "username": "irfanrosandi", "registration_date": "2017-10-20", "submission_date": ""}, {"challenge_id": 30059954, "username": "ishaqzain", "registration_date": "2017-10-20", "submission_date": ""}, {"challenge_id": 30059954, "username": "abedavera", "registration_date": "2017-10-20", "submission_date": ""}, {"challenge_id": 30059954, "username": "krisjen", "registration_date": "2017-10-20", "submission_date": ""}, {"challenge_id": 30059954, "username": "kharm", "registration_date": "2017-10-20", "submission_date": ""}, {"challenge_id": 30059954, "username": "tewibowo", "registration_date": "2017-10-20", "submission_date": "2017-10-21"}, {"challenge_id": 30059954, "username": "t3uku", "registration_date": "2017-10-20", "submission_date": "2017-10-23"}, {"challenge_id": 30059954, "username": "petetebe", "registration_date": "2017-10-20", "submission_date": ""}, {"challenge_id": 30059954, "username": "fairy_ley", "registration_date": "2017-10-20", "submission_date": "2017-10-23"}, {"challenge_id": 30059954, "username": "codingdrone", "registration_date": "2017-10-20", "submission_date": ""}, {"challenge_id": 30059954, "username": "fortunateson", "registration_date": "2017-10-20", "submission_date": ""}, {"challenge_id": 30059954, "username": "kzzu", "registration_date": "2017-10-20", "submission_date": ""}, {"challenge_id": 30059954, "username": "csy2012", "registration_date": "2017-10-20", "submission_date": ""}, {"challenge_id": 30059954, "username": "gusnendar", "registration_date": "2017-10-21", "submission_date": ""}, {"challenge_id": 30059954, "username": "iaminfinite", "registration_date": "2017-10-21", "submission_date": "2017-10-23"}, {"challenge_id": 30059954, "username": "dedetachriyanti", "registration_date": "2017-10-21", "submission_date": ""}, {"challenge_id": 30059954, "username": "joni7sunny", "registration_date": "2017-10-21", "submission_date": ""}, {"challenge_id": 30059954, "username": "penpo", "registration_date": "2017-10-21", "submission_date": ""}, {"challenge_id": 30059954, "username": "linuxuser", "registration_date": "2017-10-23", "submission_date": ""}, {"challenge_id": 30059954, "username": "almahiy", "registration_date": "2017-10-22", "submission_date": ""}, {"challenge_id": 30059954, "username": "idblack", "registration_date": "2017-10-22", "submission_date": ""}, {"challenge_id": 30059954, "username": "k.mas", "registration_date": "2017-10-22", "submission_date": ""}, {"challenge_id": 30059954, "username": "d.fachri", "registration_date": "2017-10-22", "submission_date": "2017-10-24"}, {"challenge_id": 30059954, "username": "fauzanmaulidi", "registration_date": "2017-10-22", "submission_date": ""}]