[{"challenge_id": 30099953, "username": "ngoctay", "registration_date": "2019-08-21", "submission_date": ""}, {"challenge_id": 30099953, "username": "codingdrone", "registration_date": "2019-08-21", "submission_date": ""}, {"challenge_id": 30099953, "username": "renqingwei123", "registration_date": "2019-08-22", "submission_date": ""}, {"challenge_id": 30099953, "username": "bubble99gum", "registration_date": "2019-08-22", "submission_date": ""}, {"challenge_id": 30099953, "username": "lhxhui.507", "registration_date": "2019-08-22", "submission_date": ""}, {"challenge_id": 30099953, "username": "sparemax", "registration_date": "2019-08-22", "submission_date": ""}, {"challenge_id": 30099953, "username": "phoenix103", "registration_date": "2019-08-22", "submission_date": ""}, {"challenge_id": 30099953, "username": "k.mas", "registration_date": "2019-08-22", "submission_date": ""}, {"challenge_id": 30099953, "username": "xuping.huang", "registration_date": "2019-08-22", "submission_date": "2019-08-27"}, {"challenge_id": 30099953, "username": "nauhil", "registration_date": "2019-08-22", "submission_date": ""}, {"challenge_id": 30099953, "username": "ninjadexter123", "registration_date": "2019-08-22", "submission_date": ""}, {"challenge_id": 30099953, "username": "selvamanoharan", "registration_date": "2019-08-22", "submission_date": ""}, {"challenge_id": 30099953, "username": "yog-sothoth", "registration_date": "2019-08-22", "submission_date": ""}, {"challenge_id": 30099953, "username": "jitindra2093", "registration_date": "2019-08-22", "submission_date": ""}, {"challenge_id": 30099953, "username": "[es]", "registration_date": "2019-08-22", "submission_date": ""}, {"challenge_id": 30099953, "username": "krisjen", "registration_date": "2019-08-23", "submission_date": ""}, {"challenge_id": 30099953, "username": "iamdemon", "registration_date": "2019-08-23", "submission_date": ""}, {"challenge_id": 30099953, "username": "torghul", "registration_date": "2019-08-23", "submission_date": ""}, {"challenge_id": 30099953, "username": "rahulranjanmca", "registration_date": "2019-08-24", "submission_date": ""}, {"challenge_id": 30099953, "username": "wcheung", "registration_date": "2019-08-24", "submission_date": ""}, {"challenge_id": 30099953, "username": "kavukcutolga", "registration_date": "2019-08-24", "submission_date": "2019-08-26"}, {"challenge_id": 30099953, "username": "talesforce", "registration_date": "2019-08-26", "submission_date": ""}]