[{"challenge_id": 30046670, "username": "mulish", "registration_date": "2014-10-22", "submission_date": ""}, {"challenge_id": 30046670, "username": "dombits", "registration_date": "2014-10-22", "submission_date": ""}, {"challenge_id": 30046670, "username": "sunbinbrother", "registration_date": "2014-10-23", "submission_date": ""}, {"challenge_id": 30046670, "username": "nghi85", "registration_date": "2014-10-23", "submission_date": ""}, {"challenge_id": 30046670, "username": "mhykol", "registration_date": "2014-10-23", "submission_date": ""}, {"challenge_id": 30046670, "username": "superastrom", "registration_date": "2014-10-23", "submission_date": ""}, {"challenge_id": 30046670, "username": "samsundar88", "registration_date": "2014-10-23", "submission_date": ""}, {"challenge_id": 30046670, "username": "lieutenantroger", "registration_date": "2014-10-23", "submission_date": ""}, {"challenge_id": 30046670, "username": "srmocher", "registration_date": "2014-10-24", "submission_date": ""}, {"challenge_id": 30046670, "username": "cmax", "registration_date": "2014-10-24", "submission_date": ""}, {"challenge_id": 30046670, "username": "general7078", "registration_date": "2014-10-24", "submission_date": ""}, {"challenge_id": 30046670, "username": "tgkokk", "registration_date": "2014-10-25", "submission_date": ""}, {"challenge_id": 30046670, "username": "shazzz", "registration_date": "2014-10-25", "submission_date": ""}, {"challenge_id": 30046670, "username": "gstvac", "registration_date": "2014-10-25", "submission_date": ""}, {"challenge_id": 30046670, "username": "gogocrow", "registration_date": "2014-10-26", "submission_date": "2014-10-26"}, {"challenge_id": 30046670, "username": "rushikesh.deshp", "registration_date": "2014-10-26", "submission_date": ""}, {"challenge_id": 30046670, "username": "wsobolewski", "registration_date": "2014-10-26", "submission_date": ""}]