[{"challenge_id": 30048751, "username": "mhykol", "registration_date": "2015-01-31", "submission_date": ""}, {"challenge_id": 30048751, "username": "marme", "registration_date": "2015-01-31", "submission_date": ""}, {"challenge_id": 30048751, "username": "spk256", "registration_date": "2015-01-31", "submission_date": ""}, {"challenge_id": 30048751, "username": "fcoskun", "registration_date": "2015-01-31", "submission_date": "2015-01-31"}, {"challenge_id": 30048751, "username": "antslag", "registration_date": "2015-01-31", "submission_date": ""}, {"challenge_id": 30048751, "username": "xiulin_li", "registration_date": "2015-01-31", "submission_date": "2015-01-31"}, {"challenge_id": 30048751, "username": "ashgupte", "registration_date": "2015-01-31", "submission_date": ""}, {"challenge_id": 30048751, "username": "jitrocs", "registration_date": "2015-01-31", "submission_date": ""}, {"challenge_id": 30048751, "username": "daga_sumit", "registration_date": "2015-01-31", "submission_date": ""}, {"challenge_id": 30048751, "username": "phaniram", "registration_date": "2015-01-31", "submission_date": "2015-01-31"}, {"challenge_id": 30048751, "username": "radavis", "registration_date": "2015-01-31", "submission_date": "2015-02-01"}, {"challenge_id": 30048751, "username": "ameshi", "registration_date": "2015-01-31", "submission_date": ""}, {"challenge_id": 30048751, "username": "googlesmkm", "registration_date": "2015-01-31", "submission_date": ""}, {"challenge_id": 30048751, "username": "eric.gross", "registration_date": "2015-01-31", "submission_date": ""}]