[{"challenge_id": 30047990, "username": "satheskumar", "registration_date": "2014-12-13", "submission_date": "2014-12-17"}, {"challenge_id": 30047990, "username": "kairos1725", "registration_date": "2014-12-13", "submission_date": ""}, {"challenge_id": 30047990, "username": "devasthali", "registration_date": "2014-12-13", "submission_date": ""}, {"challenge_id": 30047990, "username": "dkumar1810", "registration_date": "2014-12-14", "submission_date": "2014-12-14"}, {"challenge_id": 30047990, "username": "pixroom", "registration_date": "2014-12-14", "submission_date": ""}, {"challenge_id": 30047990, "username": "saiakhil2012", "registration_date": "2014-12-14", "submission_date": ""}, {"challenge_id": 30047990, "username": "wilxzzz", "registration_date": "2014-12-14", "submission_date": ""}, {"challenge_id": 30047990, "username": "petrus10", "registration_date": "2014-12-15", "submission_date": "2014-12-17"}, {"challenge_id": 30047990, "username": "jeniroxy", "registration_date": "2014-12-15", "submission_date": ""}, {"challenge_id": 30047990, "username": "flovey", "registration_date": "2014-12-15", "submission_date": ""}, {"challenge_id": 30047990, "username": "rekamoure", "registration_date": "2014-12-15", "submission_date": ""}, {"challenge_id": 30047990, "username": "d-zign", "registration_date": "2014-12-15", "submission_date": "2014-12-17"}, {"challenge_id": 30047990, "username": "farizzx77", "registration_date": "2014-12-15", "submission_date": ""}, {"challenge_id": 30047990, "username": "tiktok", "registration_date": "2014-12-15", "submission_date": ""}, {"challenge_id": 30047990, "username": "kreasindo", "registration_date": "2014-12-15", "submission_date": ""}, {"challenge_id": 30047990, "username": "abedavera", "registration_date": "2014-12-15", "submission_date": "2014-12-17"}, {"challenge_id": 30047990, "username": "budihartono", "registration_date": "2014-12-15", "submission_date": ""}, {"challenge_id": 30047990, "username": "handiputra", "registration_date": "2014-12-15", "submission_date": "2014-12-16"}, {"challenge_id": 30047990, "username": "nicokontes", "registration_date": "2014-12-16", "submission_date": ""}, {"challenge_id": 30047990, "username": "riopurba", "registration_date": "2014-12-16", "submission_date": "2014-12-16"}, {"challenge_id": 30047990, "username": "yoki", "registration_date": "2014-12-16", "submission_date": "2014-12-17"}, {"challenge_id": 30047990, "username": "kharm", "registration_date": "2014-12-16", "submission_date": "2014-12-16"}, {"challenge_id": 30047990, "username": "poundinc_tc", "registration_date": "2014-12-16", "submission_date": ""}, {"challenge_id": 30047990, "username": "light_ray", "registration_date": "2014-12-16", "submission_date": ""}]